[
null,
{"id":1,"battlerName":"Actor1_1","characterIndex":0,"characterName":"$idk","classId":1,"equips":[1,0,0,0,0],"faceIndex":0,"faceName":"basey","traits":[],"initialLevel":1,"maxLevel":30,"name":"Basey","nickname":"","note":"","profile":"Overall normal fella. Can use Pistolkind, Fistkind and\nSwordkind weapons when Strifing."},
{"id":2,"battlerName":"","characterIndex":0,"characterName":"$femtanyl","classId":2,"equips":[2,0,0,0,0],"faceIndex":0,"faceName":"femtanyl","traits":[],"initialLevel":1,"maxLevel":30,"name":"Token","nickname":"","note":"","profile":"Silly, injure-prone cat thing. She can use Daggerkind\nand Clawkind weapons."},
{"id":3,"battlerName":"","characterIndex":1,"characterName":"TF2_MV_RED","classId":3,"equips":[6,0,3,0,0],"faceIndex":0,"faceName":"soldia","traits":[],"initialLevel":1,"maxLevel":30,"name":"Soldier","nickname":"","note":"","profile":""},
{"id":4,"battlerName":"","characterIndex":0,"characterName":"","classId":1,"equips":[0,0,0,0,0],"faceIndex":0,"faceName":"","traits":[],"initialLevel":1,"maxLevel":99,"name":"","nickname":"","note":"","profile":""}
]